azuretoolbox/__init__.py
azuretoolbox/database.py
azuretoolbox/keyvault.py
azuretoolbox-1.0.10.dist-info/METADATA
azuretoolbox-1.0.10.dist-info/WHEEL
azuretoolbox-1.0.10.dist-info/licenses/LICENSE
azuretoolbox-1.0.10.dist-info/RECORD
