Metadata-Version: 2.4
Name: azuretoolbox
Version: 1.0.10
Summary: Tools for Azure
Project-URL: Homepage, https://github.com/ciuliene/azuretoolbox
Project-URL: Issues, https://github.com/ciuliene/azuretoolbox/issues
Author-email: Giuliano Errico <errgioul2@gmail.com>
License-File: LICENSE
Classifier: License :: OSI Approved :: MIT License
Classifier: Operating System :: OS Independent
Classifier: Programming Language :: Python :: 3
Requires-Python: >=3.11
Requires-Dist: azure-common==1.1.28
Requires-Dist: azure-core==1.35.0
Requires-Dist: azure-identity==1.23.1
Requires-Dist: azure-keyvault-secrets==4.10.0
Requires-Dist: certifi==2025.7.14
Requires-Dist: cffi==1.17.1
Requires-Dist: charset-normalizer==3.4.2
Requires-Dist: cryptography==45.0.5
Requires-Dist: idna==3.10
Requires-Dist: isodate==0.7.2
Requires-Dist: msal-extensions==1.3.1
Requires-Dist: msal==1.32.3
Requires-Dist: packaging==25.0
Requires-Dist: portalocker==3.2.0
Requires-Dist: pycparser==2.22
Requires-Dist: pyjwt==2.10.1
Requires-Dist: pyodbc==5.2.0
Requires-Dist: requests==2.32.4
Requires-Dist: six==1.17.0
Requires-Dist: typing-extensions==4.14.1
Requires-Dist: urllib3==2.5.0
